tree_sitter_mips/__init__.py
tree_sitter_mips/__init__.pyi
tree_sitter_mips/_binding.abi3.so
tree_sitter_mips/binding.c
tree_sitter_mips/py.typed
tree_sitter_mips/queries/highlights.scm
tree_sitter_mips/queries/indents.scm
tree_sitter_mips-0.2.0.dist-info/METADATA
tree_sitter_mips-0.2.0.dist-info/WHEEL
tree_sitter_mips-0.2.0.dist-info/top_level.txt
tree_sitter_mips-0.2.0.dist-info/RECORD
tree_sitter_mips-0.2.0.dist-info/licenses/LICENSE
