Metadata-Version: 2.4
Name: tree-sitter-mips
Version: 0.2.0
Summary: A syntax parser for the MIPS Instruction Set Architecture.
Author-email: Oskar Meyenburg <oskar.meyenburg@gmail.com>
License: MIT
Project-URL: Homepage, https://github.com/omeyenburg/tree-sitter-mips
Keywords: incremental,parsing,tree-sitter,mips
Classifier: Intended Audience :: Developers
Classifier: License :: OSI Approved :: MIT License
Classifier: Topic :: Software Development :: Compilers
Classifier: Topic :: Text Processing :: Linguistic
Classifier: Typing :: Typed
Requires-Python: >=3.9
License-File: LICENSE
Provides-Extra: core
Requires-Dist: tree-sitter~=0.22; extra == "core"
Dynamic: license-file
